loadimg/__init__.py
loadimg/loadimg.py
loadimg/utils.py
loadimg-0.5.0.dist-info/licenses/LICENSE
loadimg-0.5.0.dist-info/METADATA
loadimg-0.5.0.dist-info/WHEEL
loadimg-0.5.0.dist-info/entry_points.txt
loadimg-0.5.0.dist-info/top_level.txt
loadimg-0.5.0.dist-info/RECORD
