Metadata-Version: 2.4
Name: loadimg
Version: 0.5.0
Summary: a python package for loading images
Home-page: https://github.com/not-lain/loadimg
Author-email: hhichri60@gmail.com
License: Apache 2.0 License
Classifier: Topic :: Utilities
Classifier: Programming Language :: Python :: 3.9
Requires: setuptools
Requires: wheel
Requires: typing
Requires: pillow
Requires: numpy
Requires: requests
Requires: tqdm
License-File: LICENSE
Provides-Extra: testing
Requires-Dist: setuptools; extra == "testing"
Requires-Dist: wheel; extra == "testing"
Requires-Dist: typing; extra == "testing"
Requires-Dist: pillow; extra == "testing"
Requires-Dist: numpy; extra == "testing"
Requires-Dist: requests; extra == "testing"
Requires-Dist: ruff; extra == "testing"
Requires-Dist: pytest; extra == "testing"
Requires-Dist: tqdm; extra == "testing"
Dynamic: author-email
Dynamic: classifier
Dynamic: description
Dynamic: description-content-type
Dynamic: home-page
Dynamic: license
Dynamic: license-file
Dynamic: provides-extra
Dynamic: requires
Dynamic: summary
